ez_setup.py
setup.py
liveconnect/__init__.py
liveconnect/conf.py
liveconnect/exceptions.py
liveconnect/skydrive.py
liveconnect.egg-info/PKG-INFO
liveconnect.egg-info/SOURCES.txt
liveconnect.egg-info/dependency_links.txt
liveconnect.egg-info/requires.txt
liveconnect.egg-info/top_level.txt