Metadata-Version: 1.0
Name: liveconnect
Version: 0.1.113
Summary: LiveConnect OAuth adapter for Python
Home-page: http://github.com/mansam/liveconnect
Author: Samuel Lucidi
Author-email: mansam@csh.rit.edu
License: MIT
Keywords: liveconnect skydrive
Platform: UNKNOWN
